med_safety_gym/__init__.py
med_safety_gym/app.py
med_safety_gym/client.py
med_safety_gym/dipg_agent.py
med_safety_gym/dipg_environment.py
med_safety_gym/evaluation_service.py
med_safety_gym/executor.py
med_safety_gym/fastmcp_server.py
med_safety_gym/format_parser.py
med_safety_gym/green_agent.py
med_safety_gym/green_server.py
med_safety_gym/mcp_server.py
med_safety_gym/messenger.py
med_safety_gym/models.py
med_safety_gym/notebook_utils.py
med_safety_gym/run_integration_test.py
med_safety_gym/test_a2a_client.py
med_safety_gym/test_fastmcp.py
med_safety_gym/verify_docker.py
tests/conftest.py
tests/mock_purple_agent.py
tests/test_advanced_metrics.py
tests/test_dipg_client.py
tests/test_dipg_environment.py
tests/test_dipg_reward_functions.py
tests/test_evaluation_service.py
tests/test_format_parser.py
tests/test_green_eval.py
tests/test_mcp_server.py
tests/test_robust_json.py
tests/test_security.py
tests/test_security_fixes.py
openenv_dipg_safety-0.1.18.dist-info/METADATA
openenv_dipg_safety-0.1.18.dist-info/WHEEL
openenv_dipg_safety-0.1.18.dist-info/entry_points.txt
openenv_dipg_safety-0.1.18.dist-info/top_level.txt
openenv_dipg_safety-0.1.18.dist-info/RECORD
