Metadata-Version: 2.4
Name: openenv-dipg-safety
Version: 0.1.18
Summary: DIPG Safety Environment for OpenEnv
Requires-Python: >=3.11
Requires-Dist: openenv-core>=0.1.0
Requires-Dist: fastapi>=0.109.1
Requires-Dist: uvicorn[standard]>=0.24.0
Requires-Dist: requests>=2.31.0
Requires-Dist: wsproto==1.0.0
Requires-Dist: gunicorn==22.0.0
Requires-Dist: datasets
Requires-Dist: starlette>=0.36.3
Requires-Dist: idna>=3.7
Provides-Extra: agent
Requires-Dist: google-adk>=1.0.0; extra == "agent"
Requires-Dist: a2a-sdk>=0.1.0; extra == "agent"
Requires-Dist: litellm>=1.0.0; extra == "agent"
Provides-Extra: mcp
Requires-Dist: mcp>=1.0.0; extra == "mcp"
Requires-Dist: fastmcp>=0.5.0; extra == "mcp"
Provides-Extra: dev
Requires-Dist: pytest>=8.0.0; extra == "dev"
Requires-Dist: pytest-cov>=4.0.0; extra == "dev"
Requires-Dist: ipykernel>=6.29.5; extra == "dev"
Provides-Extra: visualization
Requires-Dist: matplotlib>=3.8.0; extra == "visualization"
Requires-Dist: seaborn>=0.13.0; extra == "visualization"
Requires-Dist: scipy>=1.11.0; extra == "visualization"
Requires-Dist: pandas>=2.1.0; extra == "visualization"
Requires-Dist: reportlab>=4.0.0; extra == "visualization"
